{"openapi":"3.0.0","info":{"title":"","version":"","description":null},"servers":[{"url":"http://localhost:8080","description":null,"variables":null}],"paths":{"/":{"$ref":null,"summary":null,"description":null,"get":{"tags":null,"operationId":"helloPing","summary":null,"description":null,"parameters":null,"requestBody":null,"responses":{"200":{"description":null,"content":{"text/html":{"schema":{"nullable":false,"type":"string","allOf":null,"oneOf":null,"anyOf":null,"not":null,"items":null,"properties":null,"additionalProperties":null,"format":null,"discriminator":null,"default":null,"required":null},"encoding":null}},"headers":null,"links":null},"default":{"description":null,"content":{"text/html":{"schema":{"nullable":false,"type":"string","allOf":null,"oneOf":null,"anyOf":null,"not":null,"items":null,"properties":null,"additionalProperties":null,"format":null,"discriminator":null,"default":null,"required":null},"encoding":null}},"headers":null,"links":null}},"servers":null},"put":null,"post":null,"delete":null,"options":null,"head":null,"patch":null,"trace":null,"servers":null,"parameters":null},"/json":{"$ref":null,"summary":null,"description":null,"get":{"tags":null,"operationId":"helloJson","summary":null,"description":null,"parameters":null,"requestBody":null,"responses":{"200":{"description":null,"content":{"application/json":{"schema":{"nullable":false,"type":"object","allOf":null,"oneOf":null,"anyOf":null,"not":null,"items":null,"properties":{"name":{"nullable":false,"type":"string","allOf":null,"oneOf":null,"anyOf":null,"not":null,"items":null,"properties":null,"additionalProperties":null,"format":null,"discriminator":null,"default":null,"required":null},"count":{"nullable":false,"type":"integer","allOf":null,"oneOf":null,"anyOf":null,"not":null,"items":null,"properties":null,"additionalProperties":null,"format":null,"discriminator":null,"default":null,"required":null}},"additionalProperties":null,"format":null,"discriminator":null,"default":null,"required":["name","count"]},"encoding":null}},"headers":null,"links":null},"default":{"description":null,"content":{"text/html":{"schema":{"nullable":false,"type":"string","allOf":null,"oneOf":null,"anyOf":null,"not":null,"items":null,"properties":null,"additionalProperties":null,"format":null,"discriminator":null,"default":null,"required":null},"encoding":null}},"headers":null,"links":null}},"servers":null},"put":null,"post":null,"delete":null,"options":null,"head":null,"patch":null,"trace":null,"servers":null,"parameters":null},"/octet":{"$ref":null,"summary":null,"description":null,"get":{"tags":null,"operationId":"HelloOctet","summary":null,"description":null,"parameters":null,"requestBody":null,"responses":{"200":{"description":null,"content":{"application/octet-stream":{"schema":{"nullable":false,"type":"string","allOf":null,"oneOf":null,"anyOf":null,"not":null,"items":null,"properties":null,"additionalProperties":null,"format":"binary","discriminator":null,"default":null,"required":null},"encoding":null}},"headers":null,"links":null},"default":{"description":null,"content":{"text/html":{"schema":{"nullable":false,"type":"string","allOf":null,"oneOf":null,"anyOf":null,"not":null,"items":null,"properties":null,"additionalProperties":null,"format":null,"discriminator":null,"default":null,"required":null},"encoding":null}},"headers":null,"links":null}},"servers":null},"put":null,"post":null,"delete":null,"options":null,"head":null,"patch":null,"trace":null,"servers":null,"parameters":null},"/optimistic-fail":{"$ref":null,"summary":null,"description":null,"get":{"tags":null,"operationId":"OptimisticFail","summary":null,"description":null,"parameters":null,"requestBody":null,"responses":{"200":{"description":null,"content":{"text/html":{"schema":{"nullable":false,"type":"string","allOf":null,"oneOf":null,"anyOf":null,"not":null,"items":null,"properties":null,"additionalProperties":null,"format":null,"discriminator":null,"default":null,"required":null},"encoding":null}},"headers":null,"links":null},"default":{"description":null,"content":{"text/html":{"schema":{"nullable":false,"type":"string","allOf":null,"oneOf":null,"anyOf":null,"not":null,"items":null,"properties":null,"additionalProperties":null,"format":null,"discriminator":null,"default":null,"required":null},"encoding":null}},"headers":null,"links":null}},"servers":null},"put":null,"post":null,"delete":null,"options":null,"head":null,"patch":null,"trace":null,"servers":null,"parameters":null},"/pagination/{page}":{"$ref":null,"summary":null,"description":null,"get":{"tags":null,"operationId":"Pagination","summary":null,"description":null,"parameters":[{"name":"page","in":"path","description":null,"required":false,"deprecated":false,"allowEmptyValue":false,"explode":false,"allowReserved":false,"style":null,"schema":{"nullable":false,"type":"integer","allOf":null,"oneOf":null,"anyOf":null,"not":null,"items":null,"properties":null,"additionalProperties":null,"format":null,"discriminator":null,"default":null,"required":null}},{"name":"qp","in":"query","description":null,"required":false,"deprecated":false,"allowEmptyValue":false,"explode":false,"allowReserved":false,"style":null,"schema":{"nullable":false,"type":"string","allOf":null,"oneOf":null,"anyOf":null,"not":null,"items":null,"properties":null,"additionalProperties":null,"format":null,"discriminator":null,"default":null,"required":null}}],"requestBody":null,"responses":{"200":{"description":null,"content":{"application/json":{"schema":{"nullable":false,"type":"object","allOf":null,"oneOf":null,"anyOf":null,"not":null,"items":null,"properties":{"list":{"nullable":false,"type":"array","allOf":null,"oneOf":null,"anyOf":null,"not":null,"items":{"nullable":false,"type":"string","allOf":null,"oneOf":null,"anyOf":null,"not":null,"items":null,"properties":null,"additionalProperties":null,"format":null,"discriminator":null,"default":null,"required":null},"properties":null,"additionalProperties":null,"format":null,"discriminator":null,"default":null,"required":null},"nextPage":{"nullable":false,"type":"integer","allOf":null,"oneOf":null,"anyOf":null,"not":null,"items":null,"properties":null,"additionalProperties":null,"format":null,"discriminator":null,"default":null,"required":null}},"additionalProperties":null,"format":null,"discriminator":null,"default":null,"required":["list"]},"encoding":null}},"headers":null,"links":null},"default":{"description":null,"content":{"text/html":{"schema":{"nullable":false,"type":"string","allOf":null,"oneOf":null,"anyOf":null,"not":null,"items":null,"properties":null,"additionalProperties":null,"format":null,"discriminator":null,"default":null,"required":null},"encoding":null}},"headers":null,"links":null}},"servers":null},"put":null,"post":null,"delete":null,"options":null,"head":null,"patch":null,"trace":null,"servers":null,"parameters":null},"/jsonpost":{"$ref":null,"summary":null,"description":null,"get":null,"put":null,"post":{"tags":null,"operationId":"JsonPost","summary":null,"description":null,"parameters":null,"requestBody":{"description":null,"content":{"application/json":{"schema":{"nullable":false,"type":"object","allOf":null,"oneOf":null,"anyOf":null,"not":null,"items":null,"properties":{"name":{"nullable":false,"type":"string","allOf":null,"oneOf":null,"anyOf":null,"not":null,"items":null,"properties":null,"additionalProperties":null,"format":null,"discriminator":null,"default":null,"required":null}},"additionalProperties":null,"format":null,"discriminator":null,"default":null,"required":null},"encoding":null}},"required":false},"responses":{"200":{"description":null,"content":{"application/json":{"schema":{"nullable":false,"type":"object","allOf":null,"oneOf":null,"anyOf":null,"not":null,"items":null,"properties":{"name":{"nullable":false,"type":"string","allOf":null,"oneOf":null,"anyOf":null,"not":null,"items":null,"properties":null,"additionalProperties":null,"format":null,"discriminator":null,"default":null,"required":null}},"additionalProperties":null,"format":null,"discriminator":null,"default":null,"required":null},"encoding":null}},"headers":null,"links":null},"default":{"description":null,"content":{"text/html":{"schema":{"nullable":false,"type":"string","allOf":null,"oneOf":null,"anyOf":null,"not":null,"items":null,"properties":null,"additionalProperties":null,"format":null,"discriminator":null,"default":null,"required":null},"encoding":null}},"headers":null,"links":null}},"servers":null},"delete":null,"options":null,"head":null,"patch":null,"trace":null,"servers":null,"parameters":null},"/form-upload":{"$ref":null,"summary":null,"description":null,"get":null,"put":null,"post":{"tags":null,"operationId":"FormUpload","summary":null,"description":null,"parameters":null,"requestBody":{"description":null,"content":{"application/json":{"schema":{"nullable":false,"type":"object","allOf":null,"oneOf":null,"anyOf":null,"not":null,"items":null,"properties":{"file":{"nullable":false,"type":"string","allOf":null,"oneOf":null,"anyOf":null,"not":null,"items":null,"properties":null,"additionalProperties":null,"format":"binary","discriminator":null,"default":null,"required":null},"name":{"nullable":false,"type":"string","allOf":null,"oneOf":null,"anyOf":null,"not":null,"items":null,"properties":null,"additionalProperties":null,"format":null,"discriminator":null,"default":null,"required":null}},"additionalProperties":null,"format":null,"discriminator":null,"default":null,"required":null},"encoding":null}},"required":false},"responses":{"200":{"description":null,"content":{"application/json":{"schema":{"nullable":false,"type":"object","allOf":null,"oneOf":null,"anyOf":null,"not":null,"items":null,"properties":{"name":{"nullable":false,"type":"string","allOf":null,"oneOf":null,"anyOf":null,"not":null,"items":null,"properties":null,"additionalProperties":null,"format":null,"discriminator":null,"default":null,"required":null}},"additionalProperties":null,"format":null,"discriminator":null,"default":null,"required":null},"encoding":null}},"headers":null,"links":null},"default":{"description":null,"content":{"text/html":{"schema":{"nullable":false,"type":"string","allOf":null,"oneOf":null,"anyOf":null,"not":null,"items":null,"properties":null,"additionalProperties":null,"format":null,"discriminator":null,"default":null,"required":null},"encoding":null}},"headers":null,"links":null}},"servers":null},"delete":null,"options":null,"head":null,"patch":null,"trace":null,"servers":null,"parameters":null},"/uploadprogress":{"$ref":null,"summary":null,"description":null,"get":null,"put":null,"post":{"tags":null,"operationId":"UploadProgress","summary":null,"description":null,"parameters":null,"requestBody":{"description":null,"content":{"application/octet-stream":{"schema":{"nullable":false,"type":"string","allOf":null,"oneOf":null,"anyOf":null,"not":null,"items":null,"properties":null,"additionalProperties":null,"format":"binary","discriminator":null,"default":null,"required":null},"encoding":null}},"required":false},"responses":{"200":{"description":null,"content":{"application/json":{"schema":{"nullable":false,"type":"object","allOf":null,"oneOf":null,"anyOf":null,"not":null,"items":null,"properties":{"name":{"nullable":false,"type":"string","allOf":null,"oneOf":null,"anyOf":null,"not":null,"items":null,"properties":null,"additionalProperties":null,"format":null,"discriminator":null,"default":null,"required":null}},"additionalProperties":null,"format":null,"discriminator":null,"default":null,"required":null},"encoding":null}},"headers":null,"links":null},"default":{"description":null,"content":{"text/html":{"schema":{"nullable":false,"type":"string","allOf":null,"oneOf":null,"anyOf":null,"not":null,"items":null,"properties":null,"additionalProperties":null,"format":null,"discriminator":null,"default":null,"required":null},"encoding":null}},"headers":null,"links":null}},"servers":null},"delete":null,"options":null,"head":null,"patch":null,"trace":null,"servers":null,"parameters":null},"/download":{"$ref":null,"summary":null,"description":null,"get":null,"put":null,"post":{"tags":null,"operationId":"DownloadProgress","summary":null,"description":null,"parameters":null,"requestBody":null,"responses":{"200":{"description":null,"content":{"application/octet-stream":{"schema":{"nullable":false,"type":"string","allOf":null,"oneOf":null,"anyOf":null,"not":null,"items":null,"properties":null,"additionalProperties":null,"format":"binary","discriminator":null,"default":null,"required":null},"encoding":null}},"headers":null,"links":null},"default":{"description":null,"content":{"text/html":{"schema":{"nullable":false,"type":"string","allOf":null,"oneOf":null,"anyOf":null,"not":null,"items":null,"properties":null,"additionalProperties":null,"format":null,"discriminator":null,"default":null,"required":null},"encoding":null}},"headers":null,"links":null}},"servers":null},"delete":null,"options":null,"head":null,"patch":null,"trace":null,"servers":null,"parameters":null},"/offline":{"$ref":null,"summary":null,"description":null,"get":{"tags":null,"operationId":"OfflineOp","summary":null,"description":null,"parameters":null,"requestBody":null,"responses":{"200":{"description":null,"content":{"text/html":{"schema":{"nullable":false,"type":"string","allOf":null,"oneOf":null,"anyOf":null,"not":null,"items":null,"properties":null,"additionalProperties":null,"format":null,"discriminator":null,"default":null,"required":null},"encoding":null}},"headers":null,"links":null},"default":{"description":null,"content":{"text/html":{"schema":{"nullable":false,"type":"string","allOf":null,"oneOf":null,"anyOf":null,"not":null,"items":null,"properties":null,"additionalProperties":null,"format":null,"discriminator":null,"default":null,"required":null},"encoding":null}},"headers":null,"links":null}},"servers":null},"put":null,"post":null,"delete":null,"options":null,"head":null,"patch":null,"trace":null,"servers":null,"parameters":null}},"components":null,"tags":null}